{"started":false,"bluePicks":[{"championId":-1,"isPicking":false,"isCompleted":false,"summonerName":"alleninha"},{"championId":-1,"isPicking":false,"isCompleted":false,"summonerName":""},{"championId":-1,"isPicking":false,"isCompleted":false,"summonerName":""},{"championId":-1,"isPicking":false,"isCompleted":false,"summonerName":""},{"championId":-1,"isPicking":false,"isCompleted":false,"summonerName":""}],"redPicks":[{"championId":-1,"isPicking":false,"isCompleted":false,"summonerName":"sassoperere"},{"championId":-1,"isPicking":false,"isCompleted":false,"summonerName":""},{"championId":-1,"isPicking":false,"isCompleted":false,"summonerName":""},{"championId":-1,"isPicking":false,"isCompleted":false,"summonerName":""},{"championId":-1,"isPicking":false,"isCompleted":false,"summonerName":""}],"blueBans":[{"championId":-1,"isActive":false,"isCompleted":false},{"championId":-1,"isActive":false,"isCompleted":false},{"championId":-1,"isActive":false,"isCompleted":false},{"championId":-1,"isActive":false,"isCompleted":false},{"championId":-1,"isActive":false,"isCompleted":false}],"redBans":[{"championId":-1,"isActive":false,"isCompleted":false},{"championId":-1,"isActive":false,"isCompleted":false},{"championId":-1,"isActive":false,"isCompleted":false},{"championId":-1,"isActive":false,"isCompleted":false},{"championId":-1,"isActive":false,"isCompleted":false}],"time":0,"timestamp":0,"actingSide":"none","phase":""}